{
    "spawn": "(4,6)",
    "goal": "(20,6)",
    "foreground": {
     "(3,7)": "blocks/brick2.png",
     "(4,7)": "blocks/brick2.png",
     "(5,7)": "blocks/brick2.png",
     "(5,8)": "blocks/brick2.png",
     "(5,9)": "blocks/brick2.png",
     "(5,10)": "blocks/brick2.png",
     "(6,10)": "blocks/brick2.png",
     "(7,10)": "blocks/brick2.png",
     "(8,10)": "blocks/brick2.png",
     "(9,10)": "blocks/brick2.png",
     "(10,10)": "blocks/brick2.png",
     "(11,10)": "blocks/brick2.png",
     "(12,10)": "blocks/brick2.png",
     "(13,10)": "blocks/brick2.png",
     "(14,10)": "blocks/brick2.png",
     "(15,10)": "blocks/brick2.png",
     "(14,6)": "blocks/brick2.png",
     "(16,10)": "blocks/brick2.png",
     "(17,10)": "blocks/brick2.png",
     "(18,10)": "blocks/brick2.png",
     "(18,9)": "blocks/brick2.png",
     "(18,8)": "blocks/brick2.png",
     "(18,7)": "blocks/brick2.png",
     "(19,7)": "blocks/brick2.png",
     "(20,7)": "blocks/brick2.png",
     "(10,6)": "blocks/brick1.png",
     "(21,7)": "blocks/brick1.png",
     "(21,6)": "blocks/brick1.png",
     "(21,5)": "blocks/brick1.png",
     "(21,4)": "blocks/brick1.png",
     "(20,4)": "blocks/brick1.png",
     "(19,4)": "blocks/brick1.png",
     "(18,4)": "blocks/brick1.png",
     "(2,7)": "blocks/brick1.png",
     "(2,6)": "blocks/brick1.png",
     "(2,5)": "blocks/brick1.png",
     "(2,4)": "blocks/brick1.png",
     "(3,4)": "blocks/brick1.png",
     "(4,4)": "blocks/brick1.png",
     "(5,4)": "blocks/brick1.png"
    },
    "entities": {"(5,6)": "lightCrate"},
    "water": {
     "(6,9)": 1,
     "(6,8)": 1,
     "(7,8)": 1,
     "(7,9)": 1,
     "(8,9)": 1,
     "(8,8)": 1,
     "(9,8)": 1,
     "(9,9)": 1,
     "(10,9)": 1,
     "(10,8)": 1,
     "(11,8)": 1,
     "(11,9)": 1,
     "(12,9)": 1,
     "(12,8)": 1,
     "(13,8)": 1,
     "(13,9)": 1,
     "(14,9)": 1,
     "(14,8)": 1,
     "(15,8)": 1,
     "(15,9)": 1,
     "(16,9)": 1,
     "(16,8)": 1,
     "(17,8)": 1,
     "(17,9)": 1
    },
    "sunHeight": 200,
    "sunAngle": 25,
    "sunColour": 4294953512,
    "waterColour": 4284264896
   }